MANIFEST.in
pip_desc.txt
setup.py
pyimgdown/__init__.py
pyimgdown/imgdownloader.py
pyimgdown/test.py
pyimgdown/thumbnailer.py
pyimgdown.egg-info/PKG-INFO
pyimgdown.egg-info/SOURCES.txt
pyimgdown.egg-info/dependency_links.txt
pyimgdown.egg-info/entry_points.txt
pyimgdown.egg-info/not-zip-safe
pyimgdown.egg-info/requires.txt
pyimgdown.egg-info/top_level.txt