Metadata-Version: 1.1
Name: pyimgdown
Version: 0.5.4
Summary: A module of downloading image from URL and resizing.
Home-page: https://bitbucket.org/AhnSeongHyun/pyimgdown
Author: SeongHyun.Ahn
Author-email: sh84.ahn@gmail.com
License: MIT
Keywords: image download http url
Platform: UNKNOWN
Classifier: License :: OSI Approved :: MIT License
Classifier: Development Status :: 4 - Beta
Classifier: Intended Audience :: Developers
Classifier: Programming Language :: Python :: 2.7
Classifier: Programming Language :: Python :: 3.4
Classifier: Topic :: Utilities
Classifier: Topic :: Software Development :: Libraries :: Python Modules
